vmt/__init__.py
vmt/__main__.py
vmt/appdirs.py
vmt/build.py
vmt/config.py
vmt/dmenu.py
vmt/fzf.py
vmt/initial_setup.py
vmt/media.py
vmt/options.py
vmt/prompts.py
vmt/search.py
vmt/system.py
vmt/utils.py
vmt-0.0.0.dist-info/LICENSE
vmt-0.0.0.dist-info/METADATA
vmt-0.0.0.dist-info/WHEEL
vmt-0.0.0.dist-info/entry_points.txt
vmt-0.0.0.dist-info/top_level.txt
vmt-0.0.0.dist-info/RECORD
