Metadata-Version: 2.1
Name: vmt
Version: 0.0.0
Summary: Video Media Tracker. Local, and simple method for watching and tracking a video media library.
License: GNU General Public License v3 (GPLv3)
Project-URL: repository, https://codeberg.org/johndovern/vmt
Keywords: mpv
License-File: LICENSE
Requires-Dist: python-magic
Requires-Dist: loadconf
Requires-Dist: promptx
